kakao_chat_parser/__init__.py
kakao_chat_parser-0.0.1.dist-info/LICENSE
kakao_chat_parser-0.0.1.dist-info/METADATA
kakao_chat_parser-0.0.1.dist-info/WHEEL
kakao_chat_parser-0.0.1.dist-info/top_level.txt
kakao_chat_parser-0.0.1.dist-info/RECORD
